xagg/__init__.py
xagg/_version.py
xagg/auxfuncs.py
xagg/classes.py
xagg/core.py
xagg/diag.py
xagg/export.py
xagg/options.py
xagg/wrappers.py
xagg-0.3.3.1.dist-info/licenses/LICENSE
xagg-0.3.3.1.dist-info/METADATA
xagg-0.3.3.1.dist-info/WHEEL
xagg-0.3.3.1.dist-info/top_level.txt
xagg-0.3.3.1.dist-info/RECORD
