Metadata-Version: 2.4
Name: xagg
Version: 0.3.3.1
Summary: Aggregating raster data over polygons
Home-page: https://github.com/ks905383/xagg
Author: Kevin Schwarzwald
Author-email: kevin.schwarzwald@columbia.edu
License: GNU General Public License (GPL)
Classifier: Programming Language :: Python :: 3
Classifier: License :: OSI Approved :: GNU General Public License (GPL)
Classifier: Operating System :: OS Independent
Requires-Python: >=3.8
License-File: LICENSE
Requires-Dist: numpy
Requires-Dist: scipy
Requires-Dist: xarray
Requires-Dist: pandas
Requires-Dist: netcdf4
Requires-Dist: geopandas>=0.12.0
Requires-Dist: shapely
Requires-Dist: tables
Requires-Dist: cf_xarray>=0.5.1
Provides-Extra: regrid
Requires-Dist: xesmf>=0.7.1; extra == "regrid"
Requires-Dist: esmpy>=8.1.0; extra == "regrid"
Provides-Extra: plots
Requires-Dist: matplotlib; extra == "plots"
Requires-Dist: cmocean; extra == "plots"
Requires-Dist: cartopy; extra == "plots"
Provides-Extra: numba
Requires-Dist: numba; extra == "numba"
Dynamic: author
Dynamic: author-email
Dynamic: classifier
Dynamic: description
Dynamic: description-content-type
Dynamic: home-page
Dynamic: license-file
Dynamic: provides-extra
Dynamic: requires-dist
Dynamic: requires-python
Dynamic: summary
